jv_stt_azure/__init__.py
jv_stt_azure/azure_stt.py
jv_stt_azure-1.0.1.dist-info/licenses/LICENSE
jv_stt_azure-1.0.1.dist-info/METADATA
jv_stt_azure-1.0.1.dist-info/WHEEL
jv_stt_azure-1.0.1.dist-info/top_level.txt
jv_stt_azure-1.0.1.dist-info/RECORD
