Metadata-Version: 2.4
Name: jv_stt_azure
Version: 1.0.1
Summary: Jarvis todo
Author-email: lejza <michal.lejza@gmail.com>
Project-URL: Homepage, https://github.com/lazy-one/Jarvis
Project-URL: Issues, https://github.com/lazy-one/Jarvis
Classifier: Programming Language :: Python :: 3
Classifier: License :: OSI Approved :: MIT License
Classifier: Operating System :: Microsoft :: Windows
Requires-Python: >=3.13
License-File: LICENSE
Dynamic: license-file
